Transformer/__init__.py
Transformer/controllers.py
Transformer/exceptions.py
Transformer/proxy.py
Transformer/transformer.py
Transformer/wrappers.py
kairos_transformer-1.0.0.dist-info/LICENSE
kairos_transformer-1.0.0.dist-info/METADATA
kairos_transformer-1.0.0.dist-info/WHEEL
kairos_transformer-1.0.0.dist-info/top_level.txt
kairos_transformer-1.0.0.dist-info/RECORD
