Metadata-Version: 2.1
Name: kairos-transformer
Version: 1.0.0
Summary: A powerful Python package for transforming and tracking object references.
Home-page: https://github.com/kairos-xx/transformer
Author: Joao Lopes
Author-email: joaoslopes@gmail.com
Classifier: Programming Language :: Python :: 3
Classifier: License :: OSI Approved :: MIT License
Classifier: Operating System :: OS Independent
Requires-Python: >=3.6
License-File: LICENSE
Requires-Dist: setuptools>=75.6.0
Requires-Dist: requests>=2.32.3
